[
  {
    "method": "Baseline (unpruned)",
    "dataset": "banking77",
    "sparsity": 0.0,
    "accuracy": 0.9149350649350649,
    "f1_macro": 0.9149111296773904,
    "params_total": 67012685,
    "params_nonzero": 67012685,
    "compression_ratio": 1.0,
    "inference_ms": 13.205017598067439
  },
  {
    "method": "Observability",
    "dataset": "banking77",
    "sparsity": 0.3,
    "accuracy": 0.9107142857142857,
    "f1_macro": 0.9107958594456599,
    "params_total": 62879885,
    "params_nonzero": 62879885,
    "compression_ratio": 0.9383280941511297,
    "inference_ms": 8.86936773265203
  }
]